MANIFEST.in
README
setup.cfg
setup.py
DevContest.egg-info/PKG-INFO
DevContest.egg-info/SOURCES.txt
DevContest.egg-info/dependency_links.txt
DevContest.egg-info/entry_points.txt
DevContest.egg-info/paster_plugins.txt
DevContest.egg-info/requires.txt
DevContest.egg-info/top_level.txt
DevContest.egg-info/zip-safe
devcontest/__init__.py
devcontest/websetup.py
devcontest/config/__init__.py
devcontest/config/deployment.ini_tmpl
devcontest/config/environment.py
devcontest/config/middleware.py
devcontest/config/routing.py
devcontest/controllers/__init__.py
devcontest/controllers/admin.py
devcontest/controllers/archiv.py
devcontest/controllers/auth.py
devcontest/controllers/contest.py
devcontest/controllers/error.py
devcontest/controllers/home.py
devcontest/controllers/page.py
devcontest/controllers/registration.py
devcontest/controllers/runners.py
devcontest/controllers/task.py
devcontest/controllers/user.py
devcontest/lib/__init__.py
devcontest/lib/app_globals.py
devcontest/lib/base.py
devcontest/lib/helpers.py
devcontest/lib/formbuild/__init__.py
devcontest/lib/formbuild/helpers.py
devcontest/model/__init__.py
devcontest/model/meta.py
devcontest/model/db/__init__.py
devcontest/model/db/contest.py
devcontest/model/db/runner.py
devcontest/model/db/source.py
devcontest/model/db/task.py
devcontest/model/db/user.py
devcontest/public/add.png
devcontest/public/bg.png
devcontest/public/edit.png
devcontest/public/favicon.ico
devcontest/public/header-bg2.png
devcontest/public/highlighter.css
devcontest/public/icon.ico
devcontest/public/icon.png
devcontest/public/jsmath.js
devcontest/public/my.js
devcontest/public/nav-off-bg.png
devcontest/public/pause.png
devcontest/public/play.png
devcontest/public/pylons-logo.gif
devcontest/public/python-powered-w-70x28.png
devcontest/public/remove.png
devcontest/public/repeat.png
devcontest/public/reset.png
devcontest/public/running.gif
devcontest/public/source.gif
devcontest/public/style.css
devcontest/public/test.html
devcontest/public/true.gif
devcontest/public/true.png
devcontest/public/jsmath/blank.gif
devcontest/public/jsmath/fonts.zip
devcontest/public/jsmath/jsMath-BaKoMa-fonts.js
devcontest/public/jsmath/jsMath-autoload.html
devcontest/public/jsmath/jsMath-controls.html
