Metadata-Version: 1.0
Name: DevContest
Version: 0.4
Summary: Web interface for developers contests. Python, C, Pascal, PHP, Perl, Java
Home-page: http://github.com/yetty/DevContest/tree/0.3
Author: Juda Kaleta
Author-email: juda.kaleta@gmail.com
License: GPL2
Platform: UNKNOWN
